asgi_csrf.py
asgi_csrf-0.11.dist-info/LICENSE
asgi_csrf-0.11.dist-info/METADATA
asgi_csrf-0.11.dist-info/WHEEL
asgi_csrf-0.11.dist-info/top_level.txt
asgi_csrf-0.11.dist-info/RECORD
