Metadata-Version: 2.1
Name: asgi-csrf
Version: 0.11
Summary: ASGI middleware for protecting against CSRF attacks
Author: Simon Willison
License: Apache-2.0
Project-URL: Homepage, https://github.com/simonw/asgi-csrf
Project-URL: Changelog, https://github.com/simonw/asgi-csrf/releases
Project-URL: Issues, https://github.com/simonw/asgi-csrf/issues
Project-URL: CI, https://github.com/simonw/asgi-csrf/actions
Classifier: License :: OSI Approved :: Apache Software License
Requires-Python: >=3.9
License-File: LICENSE
Requires-Dist: itsdangerous
Requires-Dist: python-multipart>=0.0.13
Provides-Extra: test
Requires-Dist: pytest; extra == "test"
Requires-Dist: pytest-asyncio; extra == "test"
Requires-Dist: httpx>=0.16; extra == "test"
Requires-Dist: starlette; extra == "test"
Requires-Dist: pytest-cov; extra == "test"
Requires-Dist: asgi-lifespan; extra == "test"
